main.py
fnos_exporter-0.2.0.dist-info/licenses/LICENSE
tests/__init__.py
tests/debug_cpu_metrics.py
tests/debug_simple_test.py
tests/test_actual_processing.py
tests/test_cpu_temp_metric.py
tests/test_memory_metrics.py
tests/test_network_metrics.py
tests/test_response_structure.py
fnos_exporter-0.2.0.dist-info/METADATA
fnos_exporter-0.2.0.dist-info/WHEEL
fnos_exporter-0.2.0.dist-info/entry_points.txt
fnos_exporter-0.2.0.dist-info/top_level.txt
fnos_exporter-0.2.0.dist-info/RECORD
