Metadata-Version: 2.4
Name: fnos-exporter
Version: 0.2.0
Summary: Prometheus Exporter for fnOS
Home-page: https://github.com/Timandes/fnos-prometheus-exporter
Author: Your Name
Author-email: your.email@example.com
License: Apache-2.0
Project-URL: Homepage, https://github.com/Timandes/fnos-prometheus-exporter
Project-URL: Repository, https://github.com/Timandes/fnos-prometheus-exporter
Requires-Python: >=3.11
License-File: LICENSE
Requires-Dist: prometheus-client>=0.20.0
Requires-Dist: fnos>=0.8.1
Dynamic: author
Dynamic: author-email
Dynamic: home-page
Dynamic: license-file
Dynamic: requires-python
